README.rst
setup.py
lvappbuilder/Build.vi
lvappbuilder/Exit.vi
lvappbuilder/VERSION
lvappbuilder/__init__.py
lvappbuilder/act.py
lvappbuilder/filterable.py
lvappbuilder/sh.py
lvappbuilder.egg-info/PKG-INFO
lvappbuilder.egg-info/SOURCES.txt
lvappbuilder.egg-info/dependency_links.txt
lvappbuilder.egg-info/requires.txt
lvappbuilder.egg-info/top_level.txt