Metadata-Version: 1.0
Name: lvappbuilder
Version: 1.0.3
Summary: API for LabVIEW Application Builder.
Home-page: https://github.com/gergelyk/pylvappbuilder
Author: Grzegorz Krason
Author-email: grzegorz@krason.biz
License: MIT
Platform: UNKNOWN
